MANIFEST.in
README.md
setup.py
ddt_envelope/__init__.py
ddt_envelope/urls.py
ddt_envelope/views.py
ddt_envelope.egg-info/PKG-INFO
ddt_envelope.egg-info/SOURCES.txt
ddt_envelope.egg-info/dependency_links.txt
ddt_envelope.egg-info/top_level.txt
ddt_envelope/templates/ddte/envelope.html